lemon_scheduler/__init__.py
lemon_scheduler/configs/__init__.py
lemon_scheduler/configs/api_config.py
lemon_scheduler/configs/local_dev_config.py
lemon_scheduler/lemon_runtime/__init__.py
lemon_scheduler/lemon_runtime/models.py
lemon_scheduler/lemon_runtime/models_template.py
lemon_scheduler/lemon_runtime/wrappers.py
lemon_scheduler/patch/__init__.py
lemon_scheduler/patch/patch_vars.py
lemon_scheduler/scheduler/__init__.py
lemon_scheduler/scheduler/executor.py
lemon_scheduler/scheduler/funcs.py
lemon_scheduler/scheduler/trigger.py
lemon_scheduler/tools/__init__.py
lemon_scheduler/tools/sync_datamodel.py
lemon_scheduler/utils/__init__.py
lemon_scheduler/utils/log.py
lemon_scheduler-0.1.4.dist-info/METADATA
lemon_scheduler-0.1.4.dist-info/WHEEL
lemon_scheduler-0.1.4.dist-info/RECORD
